{
  "sources": [
    {
      "owner": "Open-Syria",
      "repository": "data-geography",
      "tag": "v0.1.4"
    },
    {
      "owner": "Open-Syria",
      "repository": "data-universities",
      "tag": "v0.2.2",
      "requiredReadiness": {
        "minimumLevel": "profile_ready",
        "publicApi": "approved"
      }
    },
    {
      "owner": "Open-Syria",
      "repository": "data-transport",
      "tag": "v0.1.1",
      "requiredReadiness": {
        "minimumLevel": "public_directory_ready",
        "publicApi": "approved"
      }
    },
    {
      "owner": "Open-Syria",
      "repository": "data-telecom",
      "tag": "v0.1.0",
      "requiredReadiness": {
        "minimumLevel": "api_ready",
        "publicApi": "approved"
      }
    }
  ]
}
